wafer/__init__.py
wafer/context_processors.py
wafer/markdown.py
wafer/menu.py
wafer/settings.py
wafer/urls.py
wafer/utils.py
wafer/wsgi.py
wafer/compare/__init__.py
wafer/compare/admin.py
wafer/compare/templates/admin/wafer.compare/change_form.html
wafer/compare/templates/admin/wafer.compare/compare.html
wafer/compare/templates/admin/wafer.compare/compare_list.html
wafer/kv/__init__.py
wafer/kv/models.py
wafer/kv/permissions.py
wafer/kv/serializers.py
wafer/kv/urls.py
wafer/kv/utils.py
wafer/kv/views.py
wafer/kv/migrations/0001_initial.py
wafer/kv/migrations/__init__.py
wafer/kv/tests/__init__.py
wafer/kv/tests/test_kv_api.py
wafer/locale/django.pot
wafer/locale/be/LC_MESSAGES/django.mo
wafer/locale/be/LC_MESSAGES/django.po
wafer/locale/de/LC_MESSAGES/django.mo
wafer/locale/de/LC_MESSAGES/django.po
wafer/locale/fr/LC_MESSAGES/django.mo
wafer/locale/fr/LC_MESSAGES/django.po
wafer/locale/id/LC_MESSAGES/django.mo
wafer/locale/id/LC_MESSAGES/django.po
wafer/locale/it/LC_MESSAGES/django.mo
wafer/locale/it/LC_MESSAGES/django.po
wafer/locale/ml/LC_MESSAGES/django.mo
wafer/locale/ml/LC_MESSAGES/django.po
wafer/locale/nb_NO/LC_MESSAGES/django.mo
wafer/locale/nb_NO/LC_MESSAGES/django.po
wafer/locale/pt/LC_MESSAGES/django.mo
wafer/locale/pt/LC_MESSAGES/django.po
wafer/locale/pt_BR/LC_MESSAGES/django.mo
wafer/locale/pt_BR/LC_MESSAGES/django.po
wafer/locale/ru/LC_MESSAGES/django.mo
wafer/locale/ru/LC_MESSAGES/django.po
wafer/locale/sv/LC_MESSAGES/django.mo
wafer/locale/sv/LC_MESSAGES/django.po
wafer/management/__init__.py
wafer/management/commands/__init__.py
wafer/management/commands/wafer_add_default_groups.py
wafer/management/commands/wafer_emails.py
wafer/management/commands/wafer_registered_attendees.py
wafer/management/commands/wafer_speaker_contact_details.py
wafer/management/commands/wafer_speaker_tickets.py
wafer/management/commands/wafer_stats.py
wafer/management/commands/wafer_talk_video_reviewers.py
wafer/pages/__init__.py
wafer/pages/admin.py
wafer/pages/forms.py
wafer-0.16.1.dist-info/LICENSE
wafer-0.16.1.dist-info/METADATA
wafer-0.16.1.dist-info/WHEEL
wafer-0.16.1.dist-info/top_level.txt
wafer-0.16.1.dist-info/RECORD
