Metadata-Version: 2.1
Name: wafer
Version: 0.16.1
Summary: A wafer-thin Django library for running small conferences.
Home-page: http://github.com/CTPUG/wafer
Author: CTPUG
Author-email: ctpug@googlegroups.com
License: ISC
Classifier: Development Status :: 4 - Beta
Classifier: Intended Audience :: Developers
Classifier: License :: OSI Approved :: ISC License (ISCL)
Classifier: Operating System :: POSIX
Classifier: Programming Language :: Python :: 3
Classifier: Programming Language :: Python :: 3.6
Classifier: Programming Language :: Python :: 3.7
Classifier: Programming Language :: Python :: 3.8
Classifier: Framework :: Django
Classifier: Topic :: Software Development :: Libraries :: Python Modules
Classifier: Topic :: Internet :: WWW/HTTP
License-File: LICENSE
Requires-Dist: Django (<5.1,>=3.2)
Requires-Dist: bleach
Requires-Dist: bleach-allowlist
Requires-Dist: crispy-bootstrap5
Requires-Dist: diff-match-patch
Requires-Dist: django-bakery (>=0.13.0)
Requires-Dist: django-crispy-forms
Requires-Dist: django-markitup (>=4.0.0)
Requires-Dist: django-registration-redux
Requires-Dist: django-reversion
Requires-Dist: django-select2
Requires-Dist: djangorestframework
Requires-Dist: drf-extensions (>=0.5.0)
Requires-Dist: icalendar (>=4.0)
Requires-Dist: jsonfield
Requires-Dist: markdown (>=2.5)
Requires-Dist: pillow
Requires-Dist: py3dns
Requires-Dist: pyLibravatar
Requires-Dist: pytz
Requires-Dist: requests
